Py_package/__init__.py
Py_package/mod_pack.py
Py_package/first_pack/__init__.py
Py_package/first_pack/addition.py
Py_package/first_pack/subtraction.py
Py_package/second_pack/__init__.py
Py_package/second_pack/division.py
Py_package/second_pack/multiplication.py
TRICHY-0.1.dist-info/LICENSE.txt
TRICHY-0.1.dist-info/METADATA
TRICHY-0.1.dist-info/WHEEL
TRICHY-0.1.dist-info/top_level.txt
TRICHY-0.1.dist-info/RECORD
